suriin/__init__.py
suriin-0.0.22.dist-info/METADATA
suriin-0.0.22.dist-info/WHEEL
suriin-0.0.22.dist-info/licenses/LICENSE
suriin-0.0.22.dist-info/RECORD
