Metadata-Version: 2.1
Name: suriin
Version: 0.0.22
Summary: Suriin (soo-ree-ihn or sure-ree-in, depending on your pick) is a simple, lightweight, and minimalist Python library for general testing.
Project-URL: Homepage, https://gitlab.com/demo-package/demo-package-python
Project-URL: Bug Tracker, https://github.com/demo-package/demo-package-python/~/issues
Author-email: "LJ. Sta. Ana" <lvjhn.mx@gmail.com>
License: Copyright 2022 Levi John Sta. Ana
Classifier: License :: OSI Approved :: MIT License
Classifier: Operating System :: OS Independent
Classifier: Programming Language :: Python :: 3
Requires-Python: >=3.7
Requires-Dist: bleach==5.0.1
Requires-Dist: build==0.8.0
Requires-Dist: certifi==2022.6.15
Requires-Dist: cffi==1.15.1
Requires-Dist: charset-normalizer==2.1.0
Requires-Dist: commonmark==0.9.1
Requires-Dist: cryptography==37.0.4
Requires-Dist: docutils==0.19
Requires-Dist: idna==3.3
Requires-Dist: importlib-metadata==4.12.0
Requires-Dist: jeepney==0.8.0
Requires-Dist: keyring==23.6.0
Requires-Dist: packaging==21.3
Requires-Dist: pep517==0.12.0
Requires-Dist: pkginfo==1.8.3
Requires-Dist: pycparser==2.21
Requires-Dist: pygments==2.12.0
Requires-Dist: pyparsing==3.0.9
Requires-Dist: readme-renderer==35.0
Requires-Dist: requests-toolbelt==0.9.1
Requires-Dist: requests==2.28.1
Requires-Dist: rfc3986==2.0.0
Requires-Dist: rich==12.5.1
Requires-Dist: secretstorage==3.3.2
Requires-Dist: six==1.16.0
Requires-Dist: toml==0.10.2
Requires-Dist: tomli==2.0.1
Requires-Dist: twine==4.0.1
Requires-Dist: urllib3==1.26.10
Requires-Dist: webencodings==0.5.1
Requires-Dist: zipp==3.8.0
